arya/__init__.py
arya/config/__init__.py
arya/config/config.py
arya.config-2.0.0.dist-info/DESCRIPTION.rst
arya.config-2.0.0.dist-info/METADATA
arya.config-2.0.0.dist-info/RECORD
arya.config-2.0.0.dist-info/WHEEL
arya.config-2.0.0.dist-info/metadata.json
arya.config-2.0.0.dist-info/pbr.json
arya.config-2.0.0.dist-info/top_level.txt
