Metadata-Version: 2.0
Name: arya.config
Version: 2.0.0
Summary: UNKNOWN
Home-page: https://pypi.python.org/pypi/arya.config
Author: Zack Buhman
Author-email: zack@buhman.org
License: UNKNOWN
Platform: UNKNOWN
Requires-Dist: PyYAML (>=3.11)
Requires-Dist: attrdict (>=2.0.0)
Requires-Dist: pyxdg (>=0.25)
Requires-Dist: yamlordereddictloader (>=0.1.1)
